turbodrf/__init__.py
turbodrf/apps.py
turbodrf/backends.py
turbodrf/documentation.py
turbodrf/filter_backends.py
turbodrf/metadata.py
turbodrf/mixins.py
turbodrf/models.py
turbodrf/permissions.py
turbodrf/router.py
turbodrf/serializers.py
turbodrf/settings.py
turbodrf/swagger.py
turbodrf/swagger_ui.py
turbodrf/tracking.py
turbodrf/urls.py
turbodrf/user_extensions.py
turbodrf/utils.py
turbodrf/validation.py
turbodrf/views.py
turbodrf/integrations/__init__.py
turbodrf/integrations/allauth.py
turbodrf/integrations/allauth_roles.py
turbodrf/integrations/keycloak.py
turbodrf/migrations/0001_initial.py
turbodrf/migrations/__init__.py
turbodrf-0.2.3.dist-info/licenses/LICENSE
turbodrf-0.2.3.dist-info/METADATA
turbodrf-0.2.3.dist-info/WHEEL
turbodrf-0.2.3.dist-info/top_level.txt
turbodrf-0.2.3.dist-info/RECORD
