Metadata-Version: 2.4
Name: turbodrf
Version: 0.2.3
Summary: Dead simple Django REST API generator with role-based permissions
Home-page: https://github.com/alexandercollins/turbodrf
Author: Alexander Collins
Author-email: 
License: MIT
Project-URL: Homepage, https://github.com/alexandercollins/turbodrf
Project-URL: Documentation, https://turbodrf.readthedocs.io
Project-URL: Repository, https://github.com/alexandercollins/turbodrf.git
Project-URL: Bug Tracker, https://github.com/alexandercollins/turbodrf/issues
Classifier: Development Status :: 4 - Beta
Classifier: Intended Audience :: Developers
Classifier: Topic :: Software Development :: Libraries :: Python Modules
Classifier: Topic :: Internet :: WWW/HTTP :: Dynamic Content
Classifier: Topic :: Internet :: WWW/HTTP :: HTTP Servers
Classifier: License :: OSI Approved :: MIT License
Classifier: Programming Language :: Python :: 3
Classifier: Programming Language :: Python :: 3.8
Classifier: Programming Language :: Python :: 3.9
Classifier: Programming Language :: Python :: 3.10
Classifier: Programming Language :: Python :: 3.11
Classifier: Programming Language :: Python :: 3.12
Classifier: Framework :: Django
Classifier: Framework :: Django :: 3.2
Classifier: Framework :: Django :: 4.0
Classifier: Framework :: Django :: 4.1
Classifier: Framework :: Django :: 4.2
Classifier: Framework :: Django :: 5.0
Classifier: Framework :: Django :: 5.1
Requires-Python: >=3.8
License-File: LICENSE
Requires-Dist: Django>=3.2
Requires-Dist: djangorestframework>=3.12.0
Requires-Dist: drf-yasg>=1.20.0
Requires-Dist: django-filter>=2.0
Provides-Extra: dev
Requires-Dist: pytest>=6.0; extra == "dev"
Requires-Dist: pytest-django>=4.0; extra == "dev"
Requires-Dist: pytest-cov>=2.0; extra == "dev"
Requires-Dist: black>=22.0; extra == "dev"
Requires-Dist: flake8>=4.0; extra == "dev"
Requires-Dist: isort>=5.0; extra == "dev"
Requires-Dist: mypy>=0.9; extra == "dev"
Provides-Extra: docs
Requires-Dist: sphinx>=5.0; extra == "docs"
Requires-Dist: myst-parser>=2.0; extra == "docs"
Provides-Extra: allauth
Requires-Dist: django-allauth>=0.57.0; extra == "allauth"
Dynamic: home-page
Dynamic: license-file
Dynamic: requires-python
